{"edges":{"edges":[{"from":0,"to":7,"weight":1,"word":""},{"from":0,"to":24,"weight":1,"word":""},{"from":0,"to":365,"weight":1,"word":""},{"from":0,"to":931,"weight":1,"word":""},{"from":0,"to":1555,"weight":1,"word":""},{"from":0,"to":1780,"weight":1,"word":""},{"from":0,"to":1901,"weight":1,"word":""},{"from":0,"to":1925,"weight":1,"word":""},{"from":0,"to":2564,"weight":1,"word":""},{"from":0,"to":2959,"weight":1,"word":""},{"from":0,"to":4381,"weight":1,"word":""},{"from":0,"to":5024,"weight":1,"word":""},{"from":0,"to":5461,"weight":1,"word":""},{"from":0,"to":5693,"weight":1,"word":""},{"from":0,"to":5984,"weight":1,"word":""},{"from":0,"to":6119,"weight":1,"word":""},{"from":0,"to":6153,"weight":1,"word":""},{"from":0,"to":6194,"weight":1,"word":""},{"from":0,"to":6201,"weight":1,"word":""}],"word":"a"},"vertexCount":9999}